carconnectivity_connector_tronity-0.6.3.dist-info/licenses/LICENSE
carconnectivity_connectors/tronity/__init__.py
carconnectivity_connectors/tronity/_version.py
carconnectivity_connectors/tronity/connector.py
carconnectivity_connectors/tronity/vehicle.py
carconnectivity_connectors/tronity/auth/__init__.py
carconnectivity_connectors/tronity/auth/auth_util.py
carconnectivity_connectors/tronity/auth/openid_session.py
carconnectivity_connectors/tronity/auth/session_manager.py
carconnectivity_connectors/tronity/auth/tronity_session.py
carconnectivity_connectors/tronity/auth/helpers/blacklist_retry.py
carconnectivity_connectors/tronity/ui/connector_ui.py
carconnectivity_connector_tronity-0.6.3.dist-info/METADATA
carconnectivity_connector_tronity-0.6.3.dist-info/WHEEL
carconnectivity_connector_tronity-0.6.3.dist-info/top_level.txt
carconnectivity_connector_tronity-0.6.3.dist-info/RECORD
